[
    {
        "channelName":"Dr. Ahmed Hagag",
        "link":"https://youtube.com/playlist?list=PLxIvc-MGOs6ib0oK1z9C46DeKd9rRcSMY&si=yEg7IRrdioQKNMwe",
        "desc":"Operating Systems Lectures | محاضرات مادة أنظمة التشغيل"
    },
    {
        "channelName":"Software Tube",
        "link":"https://youtube.com/playlist?list=PLxIvc-MGOs6ib0oK1z9C46DeKd9rRcSMY&si=yEg7IRrdioQKNMwe",
        "desc":"شرح نظم التشغيل باللغة العربية و التوضيح قدر الامكان مع استخدام المصطلحات الانجليزية الهامة للتسهيل على الطلاب في كل مكان"
    }
]